synthtree/__init__.py
synthtree/__main__.py
synthtree/synth.py
synthtree-0.1.0.dist-info/LICENSE.txt
synthtree-0.1.0.dist-info/METADATA
synthtree-0.1.0.dist-info/WHEEL
synthtree-0.1.0.dist-info/top_level.txt
synthtree-0.1.0.dist-info/RECORD
