Metadata-Version: 2.1
Name: synthtree
Version: 0.1.0
Summary: An efficient additive synthesizer that uses a binary tree algorithm and that is both serializable and can both export to WAV and stream raw PCM
Home-page: https://github.com/Gustavo6046/synth-tree
Author: Gustavo6046
Author-email: rehermann6046@gmail.com
License: MIT
Project-URL: Issue Tracker, https://github.com/Gustavo6046/synth-tree/issues
Keywords: audio synthesis,additive synthesis,synth,sound synthesis,synthesis,binary tree,efficiency,fast
Platform: UNKNOWN
Classifier: Development Status :: 3 - Alpha
Classifier: Intended Audience :: Science/Research
Classifier: Topic :: Multimedia :: Sound/Audio :: Sound Synthesis
Classifier: License :: OSI Approved :: MIT License
Classifier: Programming Language :: Python
Classifier: Programming Language :: Python :: 3.6
Classifier: Programming Language :: Python :: 3.7
Classifier: Programming Language :: Python :: 3.8
Classifier: Programming Language :: Python :: 3.9
Requires-Python: !=3.0.*,!=3.1.*,!=3.2.*,!=3.3.*,!=3.4.*,!=3.5.*
Provides-Extra: test
Requires-Dist: mypy (>=0.790) ; extra == 'test'
Requires-Dist: mypy ; extra == 'test'
